odoo/addons/hr_expense_employee_analytic_default/README.rst
odoo/addons/hr_expense_employee_analytic_default/__init__.py
odoo/addons/hr_expense_employee_analytic_default/__manifest__.py
odoo/addons/hr_expense_employee_analytic_default/i18n/hr_expense_employee_analytic_default.pot
odoo/addons/hr_expense_employee_analytic_default/i18n/it.po
odoo/addons/hr_expense_employee_analytic_default/models/__init__.py
odoo/addons/hr_expense_employee_analytic_default/models/account_analytic_distribution_model.py
odoo/addons/hr_expense_employee_analytic_default/models/hr_expense.py
odoo/addons/hr_expense_employee_analytic_default/readme/CONFIGURE.md
odoo/addons/hr_expense_employee_analytic_default/readme/CONTRIBUTORS.md
odoo/addons/hr_expense_employee_analytic_default/readme/DESCRIPTION.md
odoo/addons/hr_expense_employee_analytic_default/readme/USAGE.md
odoo/addons/hr_expense_employee_analytic_default/static/description/icon.png
odoo/addons/hr_expense_employee_analytic_default/static/description/index.html
odoo/addons/hr_expense_employee_analytic_default/tests/__init__.py
odoo/addons/hr_expense_employee_analytic_default/tests/test_hr_expense_employee_analytic_default.py
odoo_addon_hr_expense_employee_analytic_default-17.0.1.0.0.4.dist-info/METADATA
odoo_addon_hr_expense_employee_analytic_default-17.0.1.0.0.4.dist-info/WHEEL
odoo_addon_hr_expense_employee_analytic_default-17.0.1.0.0.4.dist-info/top_level.txt
odoo_addon_hr_expense_employee_analytic_default-17.0.1.0.0.4.dist-info/RECORD
